google/protobuf/__init__.py
google/protobuf/any.py
google/protobuf/compiler/__init__.py
google/protobuf/descriptor.py
google/protobuf/descriptor_database.py
google/protobuf/descriptor_pool.py
google/protobuf/duration.py
google/protobuf/internal/__init__.py
google/protobuf/internal/api_implementation.py
google/protobuf/internal/builder.py
google/protobuf/internal/containers.py
google/protobuf/internal/decoder.py
google/protobuf/internal/encoder.py
google/protobuf/internal/enum_type_wrapper.py
google/protobuf/internal/extension_dict.py
google/protobuf/internal/field_mask.py
google/protobuf/internal/message_listener.py
google/protobuf/internal/python_edition_defaults.py
google/protobuf/internal/python_message.py
google/protobuf/internal/testing_refleaks.py
google/protobuf/internal/type_checkers.py
google/protobuf/internal/well_known_types.py
google/protobuf/internal/wire_format.py
google/protobuf/json_format.py
google/protobuf/message.py
google/protobuf/message_factory.py
google/protobuf/proto.py
google/protobuf/proto_builder.py
google/protobuf/proto_json.py
google/protobuf/proto_text.py
google/protobuf/pyext/__init__.py
google/protobuf/pyext/cpp_message.py
google/protobuf/reflection.py
google/protobuf/runtime_version.py
google/protobuf/service_reflection.py
google/protobuf/symbol_database.py
google/protobuf/testdata/__init__.py
google/protobuf/text_encoding.py
google/protobuf/text_format.py
google/protobuf/timestamp.py
google/protobuf/unknown_fields.py
google/protobuf/util/__init__.py
google/protobuf/any_pb2.py
google/protobuf/api_pb2.py
google/protobuf/compiler/plugin_pb2.py
google/protobuf/descriptor_pb2.py
google/protobuf/duration_pb2.py
google/protobuf/empty_pb2.py
google/protobuf/field_mask_pb2.py
google/protobuf/source_context_pb2.py
google/protobuf/struct_pb2.py
google/protobuf/timestamp_pb2.py
google/protobuf/type_pb2.py
google/protobuf/wrappers_pb2.py
protobuf-6.33.5.dist-info/WHEEL
protobuf-6.33.5.dist-info/METADATA
protobuf-6.33.5.dist-info/LICENSE
protobuf-6.33.5.dist-info/RECORD
